docker_registry_client_async/__init__.py
docker_registry_client_async/dockerregistryclientasync.py
docker_registry_client_async/formattedsha256.py
docker_registry_client_async/hashinggenerator.py
docker_registry_client_async/imagename.py
docker_registry_client_async/jsonbytes.py
docker_registry_client_async/manifest.py
docker_registry_client_async/py.typed
docker_registry_client_async/specs.py
docker_registry_client_async/typing.py
docker_registry_client_async/utils.py
tests/__init__.py
tests/conftest.py
tests/test_aiolibs.py
tests/test_dockerregistryclientasync.py
tests/test_dockerregistryclientasync_proxy.py
tests/test_formattedsha256.py
tests/test_hashinggenerator.py
tests/test_imagename.py
tests/test_jsonbytes.py
tests/test_manifest.py
tests/test_utils.py
tests/testutils.py
docker_registry_client_async-1.0.3.dist-info/LICENSE.md
docker_registry_client_async-1.0.3.dist-info/METADATA
docker_registry_client_async-1.0.3.dist-info/WHEEL
docker_registry_client_async-1.0.3.dist-info/top_level.txt
docker_registry_client_async-1.0.3.dist-info/RECORD
