Metadata-Version: 2.1
Name: docker-registry-client-async
Version: 1.0.3
Summary: An AIOHTTP based Python REST client for the Docker Registry.
Home-page: https://github.com/crashvb/docker-registry-client-async
Author: Richard Davis
Author-email: crashvb@gmail.com
License: Apache License 2.0
Project-URL: Bug Reports, https://github.com/crashvb/docker-registry-client-async/issues
Project-URL: Source, https://github.com/crashvb/docker-registry-client-async
Keywords: async client docker docker-registry docker-registry-client registry registry-client
Platform: UNKNOWN
Classifier: Development Status :: 5 - Production/Stable
Classifier: Intended Audience :: Developers
Classifier: License :: OSI Approved :: Apache Software License
Classifier: Programming Language :: Python :: 3
Classifier: Programming Language :: Python :: 3.8
Classifier: Programming Language :: Python :: 3.9
Classifier: Programming Language :: Python :: 3.10
Classifier: Operating System :: OS Independent
Requires-Python: >=3.8
License-File: LICENSE.md
Requires-Dist: aiodns
Requires-Dist: aiofiles
Requires-Dist: aiohttp
Requires-Dist: canonicaljson
Requires-Dist: www-authenticate
Provides-Extra: dev
Requires-Dist: black; extra == "dev"
Requires-Dist: coveralls; extra == "dev"
Requires-Dist: pylint; extra == "dev"
Requires-Dist: pytest; extra == "dev"
Requires-Dist: pytest-asyncio; extra == "dev"
Requires-Dist: pytest-cov; extra == "dev"
Requires-Dist: pytest-docker-registry-fixtures>=1.0.0; extra == "dev"
Requires-Dist: pytest-docker-squid-fixtures>=1.0.0; extra == "dev"
Requires-Dist: twine; extra == "dev"
Requires-Dist: wheel; extra == "dev"
Provides-Extra: test
Requires-Dist: pytest-xdist; extra == "test"
